odoo/addons/l10n_es_reav/README.rst
odoo/addons/l10n_es_reav/__init__.py
odoo/addons/l10n_es_reav/__manifest__.py
odoo/addons/l10n_es_reav/data/fiscal_position_taxes_reav.xml
odoo/addons/l10n_es_reav/data/fiscal_positions_reav.xml
odoo/addons/l10n_es_reav/data/tax_group_data.xml
odoo/addons/l10n_es_reav/data/taxes_reav.xml
odoo/addons/l10n_es_reav/i18n/es.po
odoo/addons/l10n_es_reav/i18n/l10n_es_reav.pot
odoo/addons/l10n_es_reav/readme/CONFIGURE.rst
odoo/addons/l10n_es_reav/readme/CONTRIBUTORS.rst
odoo/addons/l10n_es_reav/readme/DESCRIPTION.rst
odoo/addons/l10n_es_reav/readme/USAGE.rst
odoo/addons/l10n_es_reav/static/description/icon.png
odoo/addons/l10n_es_reav/static/description/index.html
odoo14_addon_l10n_es_reav-14.0.1.0.1.dev5.dist-info/METADATA
odoo14_addon_l10n_es_reav-14.0.1.0.1.dev5.dist-info/WHEEL
odoo14_addon_l10n_es_reav-14.0.1.0.1.dev5.dist-info/top_level.txt
odoo14_addon_l10n_es_reav-14.0.1.0.1.dev5.dist-info/RECORD
